pca_cj/PCA.py
pca_cj/__init__.py
pca_cj/kernel_PCA.py
pca_cj-0.2.dist-info/METADATA
pca_cj-0.2.dist-info/WHEEL
pca_cj-0.2.dist-info/top_level.txt
pca_cj-0.2.dist-info/RECORD
